pylone/__init__.py
pylone/__main__.py
pylone/apis.py
pylone/config.py
pylone/functions.py
pylone/handlers.py
pylone/layers.py
pylone/pylone.py
pylone/providers/__init__.py
pylone/providers/aws/__init__.py
pylone/providers/aws/function.py
pylone/providers/aws/iam.py
pylone/providers/aws/layer.py
pylone/providers/aws/s3.py
pylone/providers/aws/shared.py
pylone/questions/__init__.py
pylone/questions/create_function.py
pylone/questions/create_layer.py
pylone/questions/credentials.py
pylone/questions/global_config.py
pylone/utils/__init__.py
pylone/utils/changes.py
pylone/utils/checksum.py
pylone/utils/constructors.py
pylone/utils/dirs.py
pylone/utils/doppler.py
pylone/utils/gitignore.py
pylone/utils/scripts.py
pylone/utils/templates.py
pylone-1.0.1.dist-info/METADATA
pylone-1.0.1.dist-info/WHEEL
pylone-1.0.1.dist-info/entry_points.txt
pylone-1.0.1.dist-info/top_level.txt
pylone-1.0.1.dist-info/RECORD
