Metadata-Version: 2.1
Name: pylone
Version: 1.0.1
Summary: A Python Serverless framework
Home-page: https://github.com/mathix420/pylone
Author: Arnaud Gissinger
Author-email: agissing@student.42.fr
License: MIT
Classifier: Intended Audience :: Developers
Classifier: Intended Audience :: System Administrators
Classifier: Topic :: Software Development :: Build Tools
Classifier: License :: OSI Approved :: MIT License
Classifier: Programming Language :: Python :: 3 :: Only
Classifier: Programming Language :: Python :: 3.9
Classifier: Programming Language :: Python :: 3.10
Classifier: Programming Language :: Python :: 3.11
Classifier: Programming Language :: Python :: 3.12
Requires-Python: >=3.8
Requires-Dist: python-dotenv>=1.0.1
Requires-Dist: InquirerLib>=0.0.2
Requires-Dist: requests>=2.32.3
Requires-Dist: boto3>=1.35.2
Requires-Dist: PyYAML>=6.0.2
